graph_weather/__init__.py
graph_weather/data/IFSAnalysis_dataloader.py
graph_weather/data/__init__.py
graph_weather/data/const.py
graph_weather/data/dataloader.py
graph_weather/data/gencast_dataloader.py
graph_weather/data/nnja_ai.py
graph_weather/models/__init__.py
graph_weather/models/analysis.py
graph_weather/models/forecast.py
graph_weather/models/losses.py
graph_weather/models/fengwu_ghr/__init__.py
graph_weather/models/fengwu_ghr/layers.py
graph_weather/models/gencast/__init__.py
graph_weather/models/gencast/denoiser.py
graph_weather/models/gencast/sampler.py
graph_weather/models/gencast/train.py
graph_weather/models/gencast/weighted_mse_loss.py
graph_weather/models/gencast/graph/__init__.py
graph_weather/models/gencast/graph/graph_builder.py
graph_weather/models/gencast/graph/grid_mesh_connectivity.py
graph_weather/models/gencast/graph/icosahedral_mesh.py
graph_weather/models/gencast/graph/model_utils.py
graph_weather/models/gencast/layers/__init__.py
graph_weather/models/gencast/layers/decoder.py
graph_weather/models/gencast/layers/encoder.py
graph_weather/models/gencast/layers/modules.py
graph_weather/models/gencast/layers/processor.py
graph_weather/models/gencast/layers/experimental/__init__.py
graph_weather/models/gencast/layers/experimental/sparse_transformer.py
graph_weather/models/gencast/utils/__init__.py
graph_weather/models/gencast/utils/batching.py
graph_weather/models/gencast/utils/noise.py
graph_weather/models/gencast/utils/statistics.py
graph_weather/models/layers/__init__.py
graph_weather/models/layers/assimilator_decoder.py
graph_weather/models/layers/assimilator_encoder.py
graph_weather/models/layers/decoder.py
graph_weather/models/layers/encoder.py
graph_weather/models/layers/graph_net_block.py
graph_weather/models/layers/processor.py
graph_weather-1.0.94.dist-info/LICENSE
graph_weather-1.0.94.dist-info/METADATA
graph_weather-1.0.94.dist-info/WHEEL
graph_weather-1.0.94.dist-info/top_level.txt
graph_weather-1.0.94.dist-info/RECORD
