Metadata-Version: 2.2
Name: graph_weather
Version: 1.0.94
Summary: Weather Forecasting with Graph Neural Networks
Home-page: https://github.com/openclimatefix/graph_weather
Author: Jacob Bieker
Author-email: jacob@bieker.tech
License: MIT License
Classifier: Development Status :: 4 - Beta
Classifier: Intended Audience :: Developers
Classifier: Topic :: Scientific/Engineering :: Artificial Intelligence
Classifier: License :: OSI Approved :: MIT License
Classifier: Programming Language :: Python :: 3.9
License-File: LICENSE
Dynamic: author
Dynamic: author-email
Dynamic: classifier
Dynamic: description
Dynamic: description-content-type
Dynamic: home-page
Dynamic: license
Dynamic: summary
